cg_django_uaa-0.0.1.dist-info/DESCRIPTION.rst
cg_django_uaa-0.0.1.dist-info/METADATA
cg_django_uaa-0.0.1.dist-info/RECORD
cg_django_uaa-0.0.1.dist-info/WHEEL
cg_django_uaa-0.0.1.dist-info/metadata.json
cg_django_uaa-0.0.1.dist-info/top_level.txt
uaa_client/__init__.py
uaa_client/authentication.py
uaa_client/configuration.py
uaa_client/fake_uaa_provider.py
uaa_client/runtests.py
uaa_client/urls.py
uaa_client/views.py
uaa_client/static/uaa_client/fake_uaa_provider/fake-cloudgov.svg
uaa_client/templates/uaa_client/fake_uaa_provider/base.html
uaa_client/templates/uaa_client/fake_uaa_provider/index.html
uaa_client/tests/__init__.py
uaa_client/tests/test_authentication.py
uaa_client/tests/test_configuration.py
uaa_client/tests/test_docs.py
uaa_client/tests/test_views.py
uaa_client/tests/urls.py
uaa_client/tests/templates/uaa_client/login_error.html
