Metadata-Version: 2.0
Name: cg-django-uaa
Version: 0.0.1
Summary: A cloud.gov UAA authentication backend for Django
Home-page: https://github.com/18F/cg-django-uaa
Author: Atul Varma
Author-email: atul.varma@gsa.gov
License: Public Domain
Platform: UNKNOWN
Classifier: Development Status :: 3 - Alpha
Classifier: Environment :: Web Environment
Classifier: Framework :: Django
Classifier: Framework :: Django :: 1.8
Classifier: Framework :: Django :: 1.9
Classifier: Framework :: Django :: 1.10
Classifier: Intended Audience :: Developers
Classifier: License :: CC0 1.0 Universal (CC0 1.0) Public Domain Dedication
Classifier: Operating System :: OS Independent
Classifier: Programming Language :: Python
Classifier: Topic :: Software Development :: Libraries :: Python Modules
Classifier: Programming Language :: Python
Classifier: Programming Language :: Python :: 3
Classifier: Programming Language :: Python :: 3.4
Classifier: Programming Language :: Python :: 3.5
Classifier: Programming Language :: Python :: 3.6
Classifier: Topic :: Utilities
Requires-Dist: django (>=1.8,<2)
Requires-Dist: PyJWT (>=1.4.2)
Requires-Dist: requests (>=2.11.0)
